ctkmvc/controller.py
ctkmvc/interface.py
ctkmvc/model.py
ctkmvc/view.py
ctkmvc-0.0.3.dist-info/METADATA
ctkmvc-0.0.3.dist-info/WHEEL
ctkmvc-0.0.3.dist-info/licenses/LICENSE
ctkmvc-0.0.3.dist-info/RECORD
