Metadata-Version: 2.3
Name: CTkMVC
Version: 0.0.3
Summary: Base classes for easy using MVC pattern with CTk library
Project-URL: GitHub, https://github.com/ovxrhxavxn/ctkmvc
Author-email: Ivan Kirov <evankirk@vk.com>
License-File: LICENSE
Classifier: License :: OSI Approved :: MIT License
Classifier: Operating System :: OS Independent
Classifier: Programming Language :: Python :: 3
Requires-Python: >=3.7
Requires-Dist: customtkinter>=5.2.2
